bluebonnet/__init__.py
bluebonnet/plotting.py
bluebonnet/flow/__init__.py
bluebonnet/flow/flowproperties.py
bluebonnet/flow/reservoir.py
bluebonnet/fluids/__init__.py
bluebonnet/fluids/fluid.py
bluebonnet/fluids/gas.py
bluebonnet/fluids/oil.py
bluebonnet/fluids/water.py
bluebonnet/forecast/__init__.py
bluebonnet/forecast/forecast.py
bluebonnet/forecast/forecast_pressure.py
bluebonnet-0.2.2.dist-info/METADATA
bluebonnet-0.2.2.dist-info/WHEEL
bluebonnet-0.2.2.dist-info/licenses/LICENSE
bluebonnet-0.2.2.dist-info/RECORD
