Metadata-Version: 2.3
Name: bluebonnet
Version: 0.2.2
Summary: Scaling solutions for production analysis from unconventional oil and gas wells
Author-email: Frank Male <frank.male@psu.edu>, Michael Marder <marder@chaos.utexas.edu>
License: 
License-File: LICENSE
Classifier: Development Status :: 4 - Beta
Classifier: Intended Audience :: Developers
Classifier: Intended Audience :: Science/Research
Classifier: License :: OSI Approved :: BSD License
Classifier: Natural Language :: English
Classifier: Operating System :: OS Independent
Classifier: Programming Language :: Python
Classifier: Programming Language :: Python :: 3
Classifier: Programming Language :: Python :: 3.8
Classifier: Programming Language :: Python :: 3.9
Classifier: Programming Language :: Python :: 3.10
Classifier: Topic :: Scientific/Engineering
Requires-Python: <3.13,>=3.8
Requires-Dist: lmfit>=1.0
Requires-Dist: matplotlib>=3.4.3
Requires-Dist: numpy>=1.22
Requires-Dist: pandas>=1.3.4
Requires-Dist: scipy>=1.7.1
Provides-Extra: dev
Requires-Dist: jupyter>=1.0.0; extra == 'dev'
Requires-Dist: pre-commit>=2.19; extra == 'dev'
Provides-Extra: docs
Requires-Dist: furo; extra == 'docs'
Requires-Dist: myst-parser>=0.13; extra == 'docs'
Requires-Dist: nbsphinx>=0.9; extra == 'docs'
Requires-Dist: pandoc>=1.12; extra == 'docs'
Requires-Dist: sphinx-autoapi; extra == 'docs'
Requires-Dist: sphinx-copybutton; extra == 'docs'
Requires-Dist: sphinx-design; extra == 'docs'
Requires-Dist: sphinx-sitemap; extra == 'docs'
Requires-Dist: sphinx>=7.0; extra == 'docs'
Provides-Extra: test
Requires-Dist: pytest-cov>=2.12.1; extra == 'test'
Requires-Dist: pytest-mpl>=0.16; extra == 'test'
Requires-Dist: pytest-xdist>=2.4; extra == 'test'
Requires-Dist: pytest>=6.2; extra == 'test'
